genesis_explorer/.DS_Store
genesis_explorer/__init__.py
genesis_explorer/artifacts/base.py
genesis_explorer/artifacts/context.py
genesis_explorer/clients/.DS_Store
genesis_explorer/clients/base/base_aiplatform.py
genesis_explorer/clients/base/base_database.py
genesis_explorer/clients/base/base_functions.py
genesis_explorer/clients/base/base_messaging.py
genesis_explorer/clients/base/base_storage.py
genesis_explorer/clients/base/core/singleton.py
genesis_explorer/clients/factory/abstract_factory.py
genesis_explorer/clients/factory/base.py
genesis_explorer/clients/factory/gcp_factory.py
genesis_explorer/clients/gcp/aiplatform_client.py
genesis_explorer/clients/gcp/bigquery_client.py
genesis_explorer/clients/gcp/functions_client.py
genesis_explorer/clients/gcp/pub_sub_client.py
genesis_explorer/clients/gcp/storage_client.py
genesis_explorer/logger/logger.py
genesis_explorer/makers/generic_maker.py
genesis_explorer/makers/model_maker.py
genesis_explorer/makers/split_data_maker.py
genesis_explorer/prueba.ipynb
genesis_explorer/validations/.DS_Store
genesis_explorer/validations/builder.py
genesis_explorer/validations/concrete_builders/classification_builder.py
genesis_explorer/validations/concrete_builders/regression_builder.py
genesis_explorer/validations/director.py
genesis_explorer/validations/product.py
genesis_explorer-9.0.0.dist-info/METADATA
genesis_explorer-9.0.0.dist-info/WHEEL
genesis_explorer-9.0.0.dist-info/RECORD
