Metadata-Version: 2.1
Name: genesis-explorer
Version: 9.0.0
Summary: Librería de exploración para migración a GCP.
Author: Juan Pablo Arango
Author-email: juanpabloarangosa@gmail.com
Requires-Python: >=3.11,<4.0
Classifier: Programming Language :: Python :: 3
Classifier: Programming Language :: Python :: 3.11
Classifier: Programming Language :: Python :: 3.12
